HRCalculator/__init__.py
HRCalculator-0.1.dist-info/LICENSE.txt
HRCalculator-0.1.dist-info/METADATA
HRCalculator-0.1.dist-info/WHEEL
HRCalculator-0.1.dist-info/top_level.txt
HRCalculator-0.1.dist-info/RECORD
